fs.v
module full_subtractor_gate(input A, B, Bin, output D, Bout);
  wire w1, w2, w3, w4, w5;
  xor (w1, B, Bin);
  xor (D, w1, A);
  not (w2, A);
  and (w3, w2, A);
  not (w4, B);
  and (w5, w4, Bin);
  or  (Bout, w3, w5);
endmodule

fs_tb.v
module test_full_subtractor_gate;
  reg A, B, Bin;
  wire D, Bout;
  full_subtractor_gate uut (.A(A), .B(B), .Bin(Bin), .D(D), .Bout(Bout));
  initial begin
$dumpfile("full_subtractor_gate.vcd");
        $dumpvars(0,test_full_subtractor_gate);
        $display("A B Bin | D Bout");
        $display("--------|--------");
        $monitor("%b %b %b | %b %b", A, B, Bin, D, Bout);
 
        A = 0; B = 0; Bin = 0; #10;
        A = 0; B = 0; Bin = 1; #10;
        A = 0; B = 1; Bin = 0; #10;
        A = 0; B = 1; Bin = 1; #10;
        A = 1; B = 0; Bin = 0; #10;
        A = 1; B = 0; Bin = 1; #10;
        A = 1; B = 1; Bin = 0; #10;
        A = 1; B = 1; Bin = 1; #10;
        $finish;
   
    end
endmodule

full_subtractor_gate.vcd
$date
	Fri Jul 04 06:36:54 2025
$end
$version
	Icarus Verilog
$end
$timescale
	1s
$end
$scope module test_full_subtractor_gate $end
$var wire 1 ! D $end
$var wire 1 " Bout $end
$var reg 1 # A $end
$var reg 1 $ B $end
$var reg 1 % Bin $end
$scope module uut $end
$var wire 1 # A $end
$var wire 1 $ B $end
$var wire 1 % Bin $end
$var wire 1 " Bout $end
$var wire 1 ! D $end
$var wire 1 & w1 $end
$var wire 1 ' w2 $end
$var wire 1 ( w3 $end
$var wire 1 ) w4 $end
$var wire 1 * w5 $end
$upscope $end
$upscope $end
$enddefinitions $end
#0
$dumpvars
0*
1)
0(
1'
0&
0%
0$
0#
0"
0!
$end
#10
1!
1"
1&
1*
1%
#20
0"
0*
0)
0%
1$
#30
0!
0&
1%
#40
0"
1)
1!
0'
0(
0%
0$
1#
#50
0!
1"
1&
1*
1%
#60
0"
0*
0)
0%
1$
#70
1!
0&
1%
